lizhlib/__init__.py
lizhlib/utils.py
lizhlib-1.0.0.dist-info/LICENSE.txt
lizhlib-1.0.0.dist-info/METADATA
lizhlib-1.0.0.dist-info/WHEEL
lizhlib-1.0.0.dist-info/top_level.txt
lizhlib-1.0.0.dist-info/RECORD
