Metadata-Version: 2.1
Name: lizhlib
Version: 1.0.0
Summary: lizh first lib
Author: lizh
Author-email: 18810971315@163.com
License: MIT
License-File: LICENSE.txt
